devart/snowflake/__init__.py
devart/snowflake/snowflake.cp310-win32.pyd
devart/snowflake/snowflake.pyi
devart/snowflake/Snowflake/Devart.Python.SnowflakeEngine.dll
devart/snowflake/Snowflake/sqlite3.dll
devart/snowflake/sqlalchemy/__init__.py
devart_snowflake_connector-1.2.0.dist-info/LICENSE
devart_snowflake_connector-1.2.0.dist-info/METADATA
devart_snowflake_connector-1.2.0.dist-info/WHEEL
devart_snowflake_connector-1.2.0.dist-info/top_level.txt
devart_snowflake_connector-1.2.0.dist-info/RECORD
